odoo/addons/currency_rate_update_RO_BNR/README.rst
odoo/addons/currency_rate_update_RO_BNR/__init__.py
odoo/addons/currency_rate_update_RO_BNR/__manifest__.py
odoo/addons/currency_rate_update_RO_BNR/services/__init__.py
odoo/addons/currency_rate_update_RO_BNR/services/update_service_RO_BNR.py
odoo/addons/currency_rate_update_RO_BNR/tests/__init__.py
odoo/addons/currency_rate_update_RO_BNR/tests/test_currency_rate_update_ro_bnr.py
odoo11_addon_currency_rate_update_RO_BNR-11.0.1.0.0.dist-info/DESCRIPTION.rst
odoo11_addon_currency_rate_update_RO_BNR-11.0.1.0.0.dist-info/METADATA
odoo11_addon_currency_rate_update_RO_BNR-11.0.1.0.0.dist-info/RECORD
odoo11_addon_currency_rate_update_RO_BNR-11.0.1.0.0.dist-info/WHEEL
odoo11_addon_currency_rate_update_RO_BNR-11.0.1.0.0.dist-info/metadata.json
odoo11_addon_currency_rate_update_RO_BNR-11.0.1.0.0.dist-info/top_level.txt
